se_code/__init__.py
se_code/se_code.py
se_code/se_run.py
se_code/test_py.py
se_code-0.2.8.dist-info/METADATA
se_code-0.2.8.dist-info/WHEEL
se_code-0.2.8.dist-info/top_level.txt
se_code-0.2.8.dist-info/RECORD
