Metadata-Version: 2.1
Name: se-code
Version: 0.2.8
Summary: se_code 对python源代码代码加密保护，带密运行
Home-page: https://github.com/ssbuild
Author: ssbuild
Author-email: 9727464@qq.com
License: Apache 2.0
Keywords: se-code,se_code,se code
Platform: win32_AMD64
Classifier: Development Status :: 5 - Production/Stable
Classifier: Intended Audience :: Developers
Classifier: Intended Audience :: Education
Classifier: Intended Audience :: Science/Research
Classifier: License :: OSI Approved :: Apache Software License
Classifier: Programming Language :: C++
Classifier: Programming Language :: Python :: 3
Classifier: Programming Language :: Python :: 3.6
Classifier: Programming Language :: Python :: 3.7
Classifier: Programming Language :: Python :: 3.8
Classifier: Programming Language :: Python :: 3.9
Classifier: Topic :: Scientific/Engineering
Classifier: Topic :: Scientific/Engineering :: Mathematics
Classifier: Topic :: Scientific/Engineering :: Artificial Intelligence
Classifier: Topic :: Software Development
Classifier: Topic :: Software Development :: Libraries
Classifier: Topic :: Software Development :: Libraries :: Python Modules
Requires-Python: >=3, <4
Requires-Dist: se-import (>=0.0.5)
Requires-Dist: fastcrypto (>=0.0.1)
